plumpton.py
plumpton-0.1.0a2.dist-info/DESCRIPTION.rst
plumpton-0.1.0a2.dist-info/LICENSE.txt
plumpton-0.1.0a2.dist-info/METADATA
plumpton-0.1.0a2.dist-info/RECORD
plumpton-0.1.0a2.dist-info/WHEEL
plumpton-0.1.0a2.dist-info/metadata.json
plumpton-0.1.0a2.dist-info/top_level.txt
