Metadata-Version: 2.0
Name: plumpton
Version: 0.1.0a2
Summary: A Python text-based game library.
Home-page: https://thomaswoodcock.net/plumpton
Author: Thomas Woodcock
Author-email: thomas@thomaswoodcock.net
License: UNKNOWN
Project-URL: Source, https://github.com/thomaswoodcock/plumpton
